MANIFEST.in
README.rst
setup.py
kikyo_bundle/__init__.py
kikyo_bundle/config.py
kikyo_bundle/datahub.py
kikyo_bundle/oss.py
kikyo_bundle/plugin.py
kikyo_bundle/search.py
kikyo_bundle.egg-info/PKG-INFO
kikyo_bundle.egg-info/SOURCES.txt
kikyo_bundle.egg-info/dependency_links.txt
kikyo_bundle.egg-info/entry_points.txt
kikyo_bundle.egg-info/not-zip-safe
kikyo_bundle.egg-info/requires.txt
kikyo_bundle.egg-info/top_level.txt
requirements/test.txt
tests/__init__.py