Metadata-Version: 1.2
Name: kikyo-bundle
Version: 0.7.1
Summary: kikyo bundle package
Home-page: UNKNOWN
License: UNKNOWN
Platform: UNKNOWN
Requires-Python: >=3.6
